memory.v
// The memory for the CPU (and the program as well)


module memory(input READ, input WRITE, input wire [8:0] DATA, input wire [5:0] A, output reg [8:0] D);
   reg [8:0] M[63:0]; // 64 words x 9 bits per word

   always @(posedge READ) begin
	  D[8:0] = M[A[5:0]][8:0];
   end

   // Assuming READ and WRITE are not asserted at the same time
   always @(posedge WRITE) begin
	  M[A[5:0]][8:0] = DATA[8:0];
   end

   // The initial value of the memory contains the entire program
   // Data and instructions stored in the same memory makes
   // the program quite confusing. It gets more interesting when
   // writing to memory is involved as well

   // The existing program computes successive terms of the Fibonacci Series
   // Observe the value of ACOUT[8:0] (the accumulator output) at every 3rd high WRITE signal
   initial begin
	  M[00][8:0] = 9'b010001100;// clear AC to 0 by ANDing with 0
	  M[01][8:0] = 9'b000001010;// load f(n-1) in AC
	  M[02][8:0] = 9'b111001001;// write AC, f(n-1) to f(n-2)
	  M[03][8:0] = 9'b010001100;// clear AC to 0 using AND again
	  M[04][8:0] = 9'b000001011;// load f(n) in AC
	  M[05][8:0] = 9'b111001010;// write AC, f(n) to f(n-1)
	  M[06][8:0] = 9'b000001001;// add f(n-1) to AC to get f(n+1)
	  M[07][8:0] = 9'b111001011;// write AC, f(n+1) to f(n)
	  M[08][8:0] = 9'b100000000;// jump back to instruction 00
	  M[09][8:0] = 9'b000000000;// memory f(n-2), initially f(0) = 0
	  M[10][8:0] = 9'b000000001;// memory f(n-1), initially f(1) = 1
	  M[11][8:0] = 9'b000000001;// memory f(n), initially n = 2, f(2) = 1
	  M[12][8:0] = 9'b000000000;// memory 0 for clearing AC using AND
	  M[13][8:0] = 9'b000000000;
	  M[14][8:0] = 9'b000000000;
	  M[15][8:0] = 9'b000000000;
	  M[16][8:0] = 9'b000000000;
	  M[17][8:0] = 9'b000000000;
	  M[18][8:0] = 9'b000000000;
	  M[19][8:0] = 9'b000000000;
	  M[20][8:0] = 9'b000000000;
	  M[21][8:0] = 9'b000000000;
	  M[22][8:0] = 9'b000000000;
	  M[23][8:0] = 9'b000000000;
	  M[24][8:0] = 9'b000000000;
	  M[25][8:0] = 9'b000000000;
	  M[26][8:0] = 9'b000000000;
	  M[27][8:0] = 9'b000000000;
	  M[28][8:0] = 9'b000000000;
	  M[29][8:0] = 9'b000000000;
	  M[30][8:0] = 9'b000000000;
	  M[31][8:0] = 9'b000000000;
	  M[32][8:0] = 9'b000000000;
	  M[33][8:0] = 9'b000000000;
	  M[34][8:0] = 9'b000000000;
	  M[35][8:0] = 9'b000000000;
	  M[36][8:0] = 9'b000000000;
	  M[37][8:0] = 9'b000000000;
	  M[38][8:0] = 9'b000000000;
	  M[39][8:0] = 9'b000000000;
	  M[40][8:0] = 9'b000000000;
	  M[41][8:0] = 9'b000000000;
	  M[42][8:0] = 9'b000000000;
	  M[43][8:0] = 9'b000000000;
	  M[44][8:0] = 9'b000000000;
	  M[45][8:0] = 9'b000000000;
	  M[46][8:0] = 9'b000000000;
	  M[47][8:0] = 9'b000000000;
	  M[48][8:0] = 9'b000000000;
	  M[49][8:0] = 9'b000000000;
	  M[50][8:0] = 9'b000000000;
	  M[51][8:0] = 9'b000000000;
	  M[52][8:0] = 9'b000000000;
	  M[53][8:0] = 9'b000000000;
	  M[54][8:0] = 9'b000000000;
	  M[55][8:0] = 9'b000000000;
	  M[56][8:0] = 9'b000000000;
	  M[57][8:0] = 9'b000000000;
	  M[58][8:0] = 9'b000000000;
	  M[59][8:0] = 9'b000000000;
	  M[60][8:0] = 9'b000000000;
	  M[61][8:0] = 9'b000000000;
	  M[62][8:0] = 9'b000000000;
	  M[63][8:0] = 9'b000000000;
   end
endmodule // memory

dff.v
// DFF required for storing the CARRY flag from the ALU
// The DFF needs to be posedge triggered to avoid trouble


module dff(input CLK, input D, output reg Q);
   always @(posedge CLK) Q = D;
endmodule // dff

decoder.v
// 5 to 32 decoder for the hardwired control unit
// The outputs are in reverse order for convenience

// Note: The text was generated using Python code
module decoder(input wire [4:0] IN, output wire [31:0] OUT);
   assign OUT[31:0] = (IN[4:0] == 5'b00000) ? 32'b10000000000000000000000000000000 :
					  (IN[4:0] == 5'b00001) ? 32'b01000000000000000000000000000000 :
					  (IN[4:0] == 5'b00010) ? 32'b00100000000000000000000000000000 :
					  (IN[4:0] == 5'b00011) ? 32'b00010000000000000000000000000000 :
					  (IN[4:0] == 5'b00100) ? 32'b00001000000000000000000000000000 :
					  (IN[4:0] == 5'b00101) ? 32'b00000100000000000000000000000000 :
					  (IN[4:0] == 5'b00110) ? 32'b00000010000000000000000000000000 :
					  (IN[4:0] == 5'b00111) ? 32'b00000001000000000000000000000000 :
					  (IN[4:0] == 5'b01000) ? 32'b00000000100000000000000000000000 :
					  (IN[4:0] == 5'b01001) ? 32'b00000000010000000000000000000000 :
					  (IN[4:0] == 5'b01010) ? 32'b00000000001000000000000000000000 :
					  (IN[4:0] == 5'b01011) ? 32'b00000000000100000000000000000000 :
					  (IN[4:0] == 5'b01100) ? 32'b00000000000010000000000000000000 :
					  (IN[4:0] == 5'b01101) ? 32'b00000000000001000000000000000000 :
					  (IN[4:0] == 5'b01110) ? 32'b00000000000000100000000000000000 :
					  (IN[4:0] == 5'b01111) ? 32'b00000000000000010000000000000000 :
					  (IN[4:0] == 5'b10000) ? 32'b00000000000000001000000000000000 :
					  (IN[4:0] == 5'b10001) ? 32'b00000000000000000100000000000000 :
					  (IN[4:0] == 5'b10010) ? 32'b00000000000000000010000000000000 :
					  (IN[4:0] == 5'b10011) ? 32'b00000000000000000001000000000000 :
					  (IN[4:0] == 5'b10100) ? 32'b00000000000000000000100000000000 :
					  (IN[4:0] == 5'b10101) ? 32'b00000000000000000000010000000000 :
					  (IN[4:0] == 5'b10110) ? 32'b00000000000000000000001000000000 :
					  (IN[4:0] == 5'b10111) ? 32'b00000000000000000000000100000000 :
					  (IN[4:0] == 5'b11000) ? 32'b00000000000000000000000010000000 :
					  (IN[4:0] == 5'b11001) ? 32'b00000000000000000000000001000000 :
					  (IN[4:0] == 5'b11010) ? 32'b00000000000000000000000000100000 :
					  (IN[4:0] == 5'b11011) ? 32'b00000000000000000000000000010000 :
					  (IN[4:0] == 5'b11100) ? 32'b00000000000000000000000000001000 :
					  (IN[4:0] == 5'b11101) ? 32'b00000000000000000000000000000100 :
					  (IN[4:0] == 5'b11110) ? 32'b00000000000000000000000000000010 :
					  (IN[4:0] == 5'b11111) ? 32'b00000000000000000000000000000001 :
					  32'b00000000000000000000000000000000;
endmodule // decoder

counter.v
// Contains various counters required in the CPU


module counter5bit(input CLK, LD, INC, CLR, input wire [4:0] DATA, output reg [4:0] STATE);
   // 5-bit counter for the hardwired control unit
   always @(negedge CLK) begin
	  if(CLR)      STATE[4:0] <= 5'b00000;
	  else if(LD)  STATE[4:0] <= DATA[4:0];
	  else if(INC) STATE[4:0] <= STATE[4:0]+1;
   end
endmodule // counter5bit


module counter6bit(input CLK, LD, INC, CLR, input wire [5:0] DATA, output reg [5:0] STATE);
   // 6-bit counter for the program counter
   always @(negedge CLK) begin
	  if(CLR)      STATE[5:0] <= 6'b000000;
	  else if(LD)  STATE[5:0] <= DATA[5:0];
	  else if(INC) STATE[5:0] <= STATE[5:0]+1;
   end
endmodule // counter6bit


module counter9bit(input CLK, LD, INC, CLR, input wire [8:0] DATA, output reg [8:0] STATE);
   // 9-bit counter for the accumulator
   always @(negedge CLK) begin
	  if(CLR)      STATE[8:0] <= 9'b000000000;
	  else if(LD)  STATE[8:0] <= DATA[8:0];
	  else if(INC) STATE[8:0] <= STATE[8:0]+1;
   end
endmodule // counter9bit

buffer.v
// Tri state buffers for the data bus


module buffer6bit(input wire [5:0] in, input enable, output wire [5:0] out);
   // Program counter buffer
   assign out[5:0] = enable ? in[5:0] : 6'bzzzzzz;
endmodule // buffer6bit


module buffer9bit(input wire [8:0] in, input enable, output wire [8:0] out);
   // Data register buffer and memory buffer
   assign out[8:0] = enable ? in[8:0] : 9'bzzzzzzzzz;
endmodule // buffer9bit

alu.v
// The ALU with three operations: ADD, AND and SUB


module ALU(input wire [1:0] SEL, input wire [8:0] AC, input wire [8:0] DR, output ALUCARRY, output wire [8:0] OUT);
   // If SEL = 00, ADD
   // If SEL = 01, SUB
   // If SEL = 10, AND
   // IF SEL = 11, invalid, we go with AND
   assign {ALUCARRY, OUT[8:0]} = (SEL == 2'b00) ? AC[8:0] + DR[8:0] :
							  (SEL == 2'b01) ? AC[8:0] - DR[8:0] :
							  AC[8:0] & DR[8:0];
endmodule // ALU

parallel.v
// Various memory elements with only parallel load
// ability, required in the CPU


module parallel3bit(input CLK, LD, input wire [2:0] DATA, output reg[2:0] STATE);
   // 3-bit instruction register
   // Positive edge triggered to load data ahead of time.
   // Code does not work otherwise!
   // (Because then the register loads its value at the same time the input changes)
   always @(posedge CLK) begin
	  if(LD) STATE[2:0] = DATA[2:0];
   end
endmodule // parallel3bit


module parallel6bit(input CLK, LD, input wire [5:0] DATA, output reg[5:0] STATE);
   // 6-bit address register
   always @(negedge CLK) begin
	  if(LD) STATE[5:0] = DATA[5:0];
   end
endmodule // parallel6bit


module parallel9bit(input CLK, LD, input wire [8:0] DATA, output reg[8:0] STATE);
   // 9-bit data register
   always @(negedge CLK) begin
	  if(LD) STATE[8:0] = DATA[8:0];
   end
endmodule // parallel9bit

simplecpu.v
// The main CPU description
// All units are negative edge triggered
// memory.v is not included here as it is external

// IR is positive edge triggered to load its data
// beforehand, without which we run into problems
// (That is, IR loads DATA just as it changes)


`include "alu.v"
`include "buffer.v"
`include "counter.v"
`include "decoder.v"
`include "dff.v"
`include "parallel.v"


module simplecpu(input clk, input wire [8:0] D, output READ, WRITE, output wire [5:0] A, output wire [8:0] DATA);
   wire [8:0] BUS;

   // Zero and carry flags
   wire 	  ZERO, CARRY;

   // Output wires of all the registers
   // Input wires are from the data bus
   // Output of AR is simply A
   wire [5:0] PCOUT;
   wire [8:0] DROUT;
   wire [8:0] ACOUT;
   wire [2:0] IROUT;

   // Output wires of the ALU
   wire [8:0] ALUOUT;
   wire 	  ALUCARRY;

   // Counter state
   wire [4:0] STATE;

   // Decoder outputs (one-hot state) (total 14)
   wire 	  FETCH1;// 00000
   wire 	  FETCH2;// 00001
   wire 	  FETCH3;// 00010
   wire 	  ADD1;  // 10000
   wire 	  ADD2;  // 10001
   wire 	  SUB1;  // 10010
   wire 	  SUB2;  // 10011
   wire 	  AND1;  // 10100
   wire 	  AND2;  // 10101
   wire 	  INC1;  // 10110
   wire 	  JMP1;  // 11000
   wire 	  JC1;   // 11010
   wire 	  JZ1;   // 11100
   wire 	  MOV1;  // 11110

   // Conditional operation states
   wire 	  JC1VALID;
   assign JC1VALID = JC1 && CARRY; // Self-explanatory
   wire 	  JZ1VALID;
   assign JZ1VALID = JZ1 && ZERO; // Self-explanatory

   // Unused decoder outputs (18)
   wire 	  UN01;
   wire 	  UN02;
   wire 	  UN03;
   wire 	  UN04;
   wire 	  UN05;
   wire 	  UN06;
   wire 	  UN07;
   wire 	  UN08;
   wire 	  UN09;
   wire 	  UN10;
   wire 	  UN11;
   wire 	  UN12;
   wire 	  UN13;
   wire 	  UN14;
   wire 	  UN15;
   wire 	  UN16;
   wire 	  UN17;
   wire 	  UN18;

   // Control signals for the parallel load registers
   // CLK is common to all
   wire 	  ARLOAD;
   wire 	  DRLOAD;
   wire 	  IRLOAD;

   // Control signals for the counters
   wire 	  PCLOAD;
   wire 	  PCINC;
   wire 	  ACLOAD;
   wire 	  ACINC;

   // Inputs for the CARRY dff
   wire 	  CARRYCLK;
   wire 	  CARRYD;

   // Initial clear signal for PC and AC
   reg  	  INITIALCLR;

   // CPU should run only after PC and AC are cleared
   assign CLK = clk && (~INITIALCLR);

   // Control signal for the ALU
   wire [1:0] ALUSEL;

   // Control signal for the counter in the hardwired control unit
   wire 	  LOAD;
   wire 	  CLR;
   wire 	  INC;

   // Control signals for the tri-state buffers
   wire 	  MEMBUS;
   wire 	  PCBUS;
   wire 	  DRBUS;

   // Initializing the registers
   // AR, DR and IR are parallel load registers
   parallel6bit AR(.CLK(CLK), .LD(ARLOAD), .DATA(BUS[5:0]), .STATE(A[5:0]));
   parallel9bit DR(.CLK(CLK), .LD(DRLOAD), .DATA(BUS[8:0]), .STATE(DROUT[8:0]));
   parallel3bit IR(.CLK(CLK), .LD(IRLOAD), .DATA(BUS[8:6]), .STATE(IROUT[2:0]));

   // Note: I don't have a very good explanation for why this arrangement
   // of CLKs and CLRs for PC, AC and COUNT works yet.

   // PC is a counter
   counter6bit PC(.CLK(CLK), .LD(PCLOAD), .INC(PCINC), .CLR(INITIALCLR), .DATA(BUS[5:0]), .STATE(PCOUT[5:0]));

   // AC is a counter connected to the ALU outputs
   counter9bit AC(.CLK(CLK), .LD(ACLOAD), .INC(ACINC), .CLR(INITIALCLR), .DATA(ALUOUT[8:0]), .STATE(ACOUT[8:0]));
   ALU ALU1(.SEL(ALUSEL[1:0]), .AC(ACOUT[8:0]), .DR(BUS[8:0]), .ALUCARRY(ALUCARRY), .OUT(ALUOUT[8:0]));

   // Tri-state buffers for the data bus
   buffer6bit PCBUF(.in(PCOUT[5:0]), .enable(PCBUS), .out(BUS[5:0]));
   buffer9bit DRBUF(.in(DROUT[8:0]), .enable(DRBUS), .out(BUS[8:0]));
   buffer9bit MEMBUF(.in(D[8:0]), .enable(MEMBUS), .out(BUS[8:0]));

   // The counter and decoder for the control unit
   // Counter has data inputs {1, IR[2:0], 0}
   // Counter uses clk directly (as CLR clears it)
   // Decoder has outputs as the one-hot states and some unused outputs
   counter5bit COUNT(.CLK(clk), .LD(LOAD), .INC(INC), .CLR(CLR), .DATA({1'b1, IROUT[2:0], 1'b0}), .STATE(STATE[4:0]));
   decoder DEC(.IN(STATE[4:0]), .OUT({FETCH1, FETCH2, FETCH3, UN01, UN02, UN03, UN04, UN05, UN06, UN07, UN08, UN09, UN10, UN11, UN12, UN13, ADD1, ADD2, SUB1, SUB2, AND1, AND2, INC1, UN14, JMP1, UN15, JC1, UN16, JZ1, UN17, MOV1, UN18}));

   // Combinational logic for the control signals
   // Combinational logic for the STATE counter
   // STATE needs to be set to zero in the beginning
   // The STATE counter uses clk directly as only synchronous reset is available
   assign CLR = ADD2 || AND2 || SUB2 || INC1 || JMP1 || JC1 || JZ1 || MOV1 || INITIALCLR;
   assign INC = FETCH1 || FETCH2 || ADD1 || AND1 || SUB1;
   assign LOAD = FETCH3;

   // Control signals for the tri-state buffers
   assign PCBUS = FETCH1;
   assign DRBUS = FETCH3 || ADD2 || AND2 || SUB2 || JMP1 || JC1VALID || JZ1VALID;
   assign MEMBUS = FETCH2 || ADD1 || AND1 || SUB1;

   // Control signals for the registers
   assign ARLOAD = FETCH1 || FETCH3;
   assign PCLOAD = JMP1 || JC1VALID || JZ1VALID;
   assign PCINC = FETCH2;
   assign DRLOAD = FETCH2 || ADD1 || AND1 || SUB1;
   assign ACLOAD = ADD2 || AND2 || SUB2;
   assign ACINC = INC1;
   assign IRLOAD = FETCH3;
   assign ALUSEL[1:0] = {AND2, SUB2};

   // Control signal for the READ output
   assign READ = FETCH2 || ADD1 || AND1 || SUB1;

   // Control signal and data for the WRITE output
   assign WRITE = MOV1;
   assign DATA[8:0] = ACOUT[8:0];

   // Zero flag
   assign ZERO = ~(ACOUT[0] || ACOUT[1] || ACOUT[2] || ACOUT[3] || ACOUT[4] || ACOUT[5] || ACOUT[6] || ACOUT[7] || ACOUT[8]);

   // Carry flag register
   // Carry becomes 1 if addition is done that exceeds the range
   // Carry is set to 0 on SUB, AND or INC
   dff CARRYFF(.CLK(CARRYCLK), .D(CARRYD), .Q(CARRY));
   assign CARRYCLK = ADD2 || SUB2 || AND2 || INC1;
   assign CARRYD = (ALUCARRY && ADD2);

   initial begin
	  // Set program counter to zero
	  // Set accumulator to zero
	  // Set state to FETCH1
	  INITIALCLR = 1;
   end

   // May need to start with clk=1 because of this
   always @(negedge clk) begin
	  INITIALCLR = 0;
   end
endmodule // simplecpu

testbench.v
// The testbench for the CPU
// Programming is done by editing memory.v


`include "simplecpu.v"
`include "memory.v"


module test();
   reg clk;
   wire READ;
   wire WRITE;
   wire [8:0] DATA;
   wire [8:0] D;
   wire [5:0] A;

   simplecpu CPU(.clk(clk), .D(D[8:0]), .READ(READ), .WRITE(WRITE), .A(A[5:0]), .DATA(DATA[8:0]));
   memory M(.READ(READ), .WRITE(WRITE), .DATA(DATA[8:0]), .A(A[5:0]), .D(D[8:0]));

   initial begin
	  clk = 1;
	  $dumpvars();
	  #1000 $finish;
   end

   always #1 clk = ~clk;
endmodule // test

dump.vcd
$date
	Fri Apr  1 14:12:28 2016
$end
$version
	Icarus Verilog
$end
$timescale
	1s
$end
$scope module test $end
$var wire 6 ! A [5:0] $end
$var wire 9 " D [8:0] $end
$var wire 9 # DATA [8:0] $end
$var wire 1 $ READ $end
$var wire 1 % WRITE $end
$var reg 1 & clk $end
$scope module CPU $end
$var wire 6 ' A [5:0] $end
$var wire 1 ( ACINC $end
$var wire 1 ) ACLOAD $end
$var wire 9 * ACOUT [8:0] $end
$var wire 1 + ADD1 $end
$var wire 1 , ADD2 $end
$var wire 1 - ALUCARRY $end
$var wire 9 . ALUOUT [8:0] $end
$var wire 2 / ALUSEL [1:0] $end
$var wire 1 0 AND1 $end
$var wire 1 1 AND2 $end
$var wire 1 2 ARLOAD $end
$var wire 9 3 BUS [8:0] $end
$var wire 1 4 CARRY $end
$var wire 1 5 CARRYCLK $end
$var wire 1 6 CARRYD $end
$var wire 1 7 CLK $end
$var wire 1 8 CLR $end
$var wire 9 9 D [8:0] $end
$var wire 9 : DATA [8:0] $end
$var wire 1 ; DRBUS $end
$var wire 1 < DRLOAD $end
$var wire 9 = DROUT [8:0] $end
$var wire 1 > FETCH1 $end
$var wire 1 ? FETCH2 $end
$var wire 1 @ FETCH3 $end
$var wire 1 A INC $end
$var wire 1 B INC1 $end
$var wire 1 C IRLOAD $end
$var wire 3 D IROUT [2:0] $end
$var wire 1 E JC1 $end
$var wire 1 F JC1VALID $end
$var wire 1 G JMP1 $end
$var wire 1 H JZ1 $end
$var wire 1 I JZ1VALID $end
$var wire 1 J LOAD $end
$var wire 1 K MEMBUS $end
$var wire 1 L MOV1 $end
$var wire 1 M PCBUS $end
$var wire 1 N PCINC $end
$var wire 1 O PCLOAD $end
$var wire 6 P PCOUT [5:0] $end
$var wire 1 $ READ $end
$var wire 5 Q STATE [4:0] $end
$var wire 1 R SUB1 $end
$var wire 1 S SUB2 $end
$var wire 1 T UN01 $end
$var wire 1 U UN02 $end
$var wire 1 V UN03 $end
$var wire 1 W UN04 $end
$var wire 1 X UN05 $end
$var wire 1 Y UN06 $end
$var wire 1 Z UN07 $end
$var wire 1 [ UN08 $end
$var wire 1 \ UN09 $end
$var wire 1 ] UN10 $end
$var wire 1 ^ UN11 $end
$var wire 1 _ UN12 $end
$var wire 1 ` UN13 $end
$var wire 1 a UN14 $end
$var wire 1 b UN15 $end
$var wire 1 c UN16 $end
$var wire 1 d UN17 $end
$var wire 1 e UN18 $end
$var wire 1 % WRITE $end
$var wire 1 f ZERO $end
$var wire 1 g clk $end
$var reg 1 h INITIALCLR $end
$scope module AR $end
$var wire 1 7 CLK $end
$var wire 6 i DATA [5:0] $end
$var wire 1 2 LD $end
$var reg 6 j STATE [5:0] $end
$upscope $end
$scope module DR $end
$var wire 1 7 CLK $end
$var wire 9 k DATA [8:0] $end
$var wire 1 < LD $end
$var reg 9 l STATE [8:0] $end
$upscope $end
$scope module IR $end
$var wire 1 7 CLK $end
$var wire 3 m DATA [2:0] $end
$var wire 1 C LD $end
$var reg 3 n STATE [2:0] $end
$upscope $end
$scope module PC $end
$var wire 1 7 CLK $end
$var wire 1 o CLR $end
$var wire 6 p DATA [5:0] $end
$var wire 1 N INC $end
$var wire 1 O LD $end
$var reg 6 q STATE [5:0] $end
$upscope $end
$scope module AC $end
$var wire 1 7 CLK $end
$var wire 1 o CLR $end
$var wire 9 r DATA [8:0] $end
$var wire 1 ( INC $end
$var wire 1 ) LD $end
$var reg 9 s STATE [8:0] $end
$upscope $end
$scope module ALU1 $end
$var wire 9 t AC [8:0] $end
$var wire 1 - ALUCARRY $end
$var wire 9 u DR [8:0] $end
$var wire 9 v OUT [8:0] $end
$var wire 2 w SEL [1:0] $end
$upscope $end
$scope module PCBUF $end
$var wire 1 M enable $end
$var wire 6 x in [5:0] $end
$var wire 6 y out [5:0] $end
$upscope $end
$scope module DRBUF $end
$var wire 1 ; enable $end
$var wire 9 z in [8:0] $end
$var wire 9 { out [8:0] $end
$upscope $end
$scope module MEMBUF $end
$var wire 1 K enable $end
$var wire 9 | in [8:0] $end
$var wire 9 } out [8:0] $end
$upscope $end
$scope module COUNT $end
$var wire 1 g CLK $end
$var wire 1 8 CLR $end
$var wire 5 ~ DATA [4:0] $end
$var wire 1 A INC $end
$var wire 1 J LD $end
$var reg 5 !" STATE [4:0] $end
$upscope $end
$scope module DEC $end
$var wire 5 "" IN [4:0] $end
$var wire 32 #" OUT [31:0] $end
$upscope $end
$scope module CARRYFF $end
$var wire 1 5 CLK $end
$var wire 1 6 D $end
$var reg 1 $" Q $end
$upscope $end
$upscope $end
$scope module M $end
$var wire 6 %" A [5:0] $end
$var wire 9 &" DATA [8:0] $end
$var wire 1 $ READ $end
$var wire 1 % WRITE $end
$var reg 9 '" D [8:0] $end
$upscope $end
$upscope $end
$enddefinitions $end
#0
$dumpvars
bx '"
b0 &"
bx %"
x$"
bx #"
bx ""
bx !"
b1xxx0 ~
bx }
bx |
bx {
bx z
bx y
b0 x
bx w
bx v
bx u
b0 t
b0 s
bx r
b0 q
bx p
1o
bx n
bx m
bx l
bx k
bx j
bx i
1h
1g
1f
xe
xd
xc
xb
xa
x`
x_
x^
x]
x\
x[
xZ
xY
xX
xW
xV
xU
xT
xS
xR
bx Q
b0 P
xO
xN
xM
xL
xK
xJ
xI
xH
xG
xF
xE
bx D
xC
xB
xA
x@
x?
x>
bx =
x<
x;
b0 :
bx 9
18
07
x6
x5
x4
bx 3
x2
x1
x0
bx /
bx .
x-
x,
x+
b0 *
x)
x(
bx '
1&
x%
x$
b0 #
bx "
bx !
$end
#1
b0 i
bz m
b0 p
bz000000 3
bz000000 k
bz000000 u
bz000000 {
bz000000 }
0;
0O
0$
0<
0K
1A
0I
0F
05
0)
06
12
b0 y
0e
0L
0%
0d
0H
0c
0E
0b
0G
0a
0B
0(
01
00
b0 /
b0 w
0S
0R
0,
0+
0`
0_
0^
0]
0\
0[
0Z
0Y
0X
0W
0V
0U
0T
0@
0C
0J
0?
0N
1>
1M
b10000000000000000000000000000000 #"
b0 !"
b0 Q
b0 ""
08
0h
0o
0&
0g
#2
17
1&
1g
#3
b10001100 .
b10001100 r
b10001100 v
0-
b10 m
b10001100 '"
b10001100 "
b10001100 9
b10001100 |
1$
1<
1K
b1100 i
b1100 p
02
bz y
b10001100 3
b10001100 k
b10001100 u
b10001100 {
b10001100 }
1?
1N
0>
0M
b1000000000000000000000000000000 #"
b1 !"
b1 Q
b1 ""
b0 j
b0 !
b0 '
b0 %"
07
0&
0g
#4
17
1&
1g
#5
1;
b10001100 .
b10001100 r
b10001100 v
0-
b1100 i
b10 m
b1100 p
b10001100 3
b10001100 k
b10001100 u
b10001100 {
b10001100 }
0A
0$
0<
0K
12
1@
1C
1J
0?
0N
b100000000000000000000000000000 #"
b1 q
b1 P
b1 x
b10 !"
b10 Q
b10 ""
b10001100 l
b10001100 =
b10001100 z
07
0&
0g
#6
b10 n
b10100 ~
b10 D
17
1&
1g
#7
b0 '"
b0 "
b0 9
b0 |
1$
1<
1K
1A
10
b0 .
b0 r
b0 v
0-
b0 i
b0 m
b0 p
b0 3
b0 k
b0 u
b0 {
b0 }
0;
02
0@
0C
0J
b100000000000 #"
b10100 !"
b10100 Q
b10100 ""
b1100 j
b1100 !
b1100 '
b1100 %"
07
0&
0g
#8
17
1&
1g
#9
18
1;
b0 i
b0 m
b0 p
0$"
04
b0 3
b0 k
b0 u
b0 {
b0 }
15
1)
0$
0<
0K
0A
b10 /
b10 w
11
00
b10000000000 #"
b10101 !"
b10101 Q
b10101 ""
b0 l
b0 =
b0 z
07
0&
0g
#10
17
1&
1g
#11
08
bz m
0;
1A
bx .
bx r
bx v
x-
05
0)
b1 i
b1 p
12
b1 y
bz000001 3
bz000001 k
bz000001 u
bz000001 {
bz000001 }
b0 /
b0 w
01
1>
1M
b10000000000000000000000000000000 #"
b0 !"
b0 Q
b0 ""
07
0&
0g
#12
17
1&
1g
#13
b1010 .
b1010 r
b1010 v
0-
b0 m
b1010 '"
b1010 "
b1010 9
b1010 |
1$
1<
1K
b1010 i
b1010 p
02
bz y
b1010 3
b1010 k
b1010 u
b1010 {
b1010 }
1?
1N
0>
0M
b1000000000000000000000000000000 #"
b1 !"
b1 Q
b1 ""
b1 j
b1 !
b1 '
b1 %"
07
0&
0g
#14
17
1&
1g
#15
1;
b1010 .
b1010 r
b1010 v
0-
b1010 i
b0 m
b1010 p
b1010 3
b1010 k
b1010 u
b1010 {
b1010 }
0A
0$
0<
0K
12
1@
1C
1J
0?
0N
b100000000000000000000000000000 #"
b10 q
b10 P
b10 x
b10 !"
b10 Q
b10 ""
b1010 l
b1010 =
b1010 z
07
0&
0g
#16
b0 n
b10000 ~
b0 D
17
1&
1g
#17
b1 '"
b1 "
b1 9
b1 |
1$
1<
1K
1A
1+
b1 .
b1 r
b1 v
0-
b1 i
b0 m
b1 p
b1 3
b1 k
b1 u
b1 {
b1 }
0;
02
0@
0C
0J
b1000000000000000 #"
b10000 !"
b10000 Q
b10000 ""
b1010 j
b1010 !
b1010 '
b1010 %"
07
0&
0g
#18
17
1&
1g
#19
18
06
1;
b1 .
b1 r
b1 v
0-
b1 i
b0 m
b1 p
b1 3
b1 k
b1 u
b1 {
b1 }
15
0$
0<
0K
0A
1)
1,
0+
b100000000000000 #"
b10001 !"
b10001 Q
b10001 ""
b1 l
b1 =
b1 z
07
0&
0g
#20
17
1&
1g
#21
0f
bz m
08
0;
1A
05
x-
0)
b10 i
b10 p
12
b10 y
bz000010 3
bz000010 k
bz000010 u
bz000010 {
bz000010 }
bx .
bx r
bx v
0,
1>
1M
b10000000000000000000000000000000 #"
b1 s
b1 *
b1 t
b1 #
b1 :
b1 &"
b0 !"
b0 Q
b0 ""
07
0&
0g
#22
17
1&
1g
#23
b111001010 .
b111001010 r
b111001010 v
0-
b111 m
b111001001 '"
b111001001 "
b111001001 9
b111001001 |
1$
1<
1K
b1001 i
b1001 p
02
bz y
b111001001 3
b111001001 k
b111001001 u
b111001001 {
b111001001 }
1?
1N
0>
0M
b1000000000000000000000000000000 #"
b1 !"
b1 Q
b1 ""
b10 j
b10 !
b10 '
b10 %"
07
0&
0g
#24
17
1&
1g
#25
1;
b111001010 .
b111001010 r
b111001010 v
0-
b1001 i
b111 m
b1001 p
b111001001 3
b111001001 k
b111001001 u
b111001001 {
b111001001 }
0A
0$
0<
0K
12
1@
1C
1J
0?
0N
b100000000000000000000000000000 #"
b11 q
b11 P
b11 x
b10 !"
b10 Q
b10 ""
b111001001 l
b111001001 =
b111001001 z
07
0&
0g
#26
b111 n
b11110 ~
b111 D
17
1&
1g
#27
18
1L
1%
bx .
bx r
bx v
x-
bz i
bz m
bz p
bz 3
bz k
bz u
bz {
bz }
0;
02
0@
0C
0J
b10 #"
b11110 !"
b11110 Q
b11110 ""
b1001 j
b1001 !
b1001 '
b1001 %"
07
0&
0g
#28
17
1&
1g
#29
1A
08
b11 i
b11 p
12
b11 y
bz000011 3
bz000011 k
bz000011 u
bz000011 {
bz000011 }
0L
0%
1>
1M
b10000000000000000000000000000000 #"
b0 !"
b0 Q
b0 ""
07
0&
0g
#30
17
1&
1g
#31
b10001101 .
b10001101 r
b10001101 v
0-
b10 m
b10001100 '"
b10001100 "
b10001100 9
b10001100 |
1$
1<
1K
b1100 i
b1100 p
02
bz y
b10001100 3
b10001100 k
b10001100 u
b10001100 {
b10001100 }
1?
1N
0>
0M
b1000000000000000000000000000000 #"
b1 !"
b1 Q
b1 ""
b11 j
b11 !
b11 '
b11 %"
07
0&
0g
#32
17
1&
1g
#33
1;
b10001101 .
b10001101 r
b10001101 v
0-
b1100 i
b10 m
b1100 p
b10001100 3
b10001100 k
b10001100 u
b10001100 {
b10001100 }
0A
0$
0<
0K
12
1@
1C
1J
0?
0N
b100000000000000000000000000000 #"
b100 q
b100 P
b100 x
b10 !"
b10 Q
b10 ""
b10001100 l
b10001100 =
b10001100 z
07
0&
0g
#34
b10 n
b10100 ~
b10 D
17
1&
1g
#35
b0 '"
b0 "
b0 9
b0 |
1$
1<
1K
1A
10
b1 .
b1 r
b1 v
0-
b0 i
b0 m
b0 p
b0 3
b0 k
b0 u
b0 {
b0 }
0;
02
0@
0C
0J
b100000000000 #"
b10100 !"
b10100 Q
b10100 ""
b1100 j
b1100 !
b1100 '
b1100 %"
07
0&
0g
#36
17
1&
1g
#37
18
1;
b0 i
b0 m
b0 p
b0 3
b0 k
b0 u
b0 {
b0 }
b0 .
b0 r
b0 v
15
1)
0$
0<
0K
0A
b10 /
b10 w
11
00
b10000000000 #"
b10101 !"
b10101 Q
b10101 ""
b0 l
b0 =
b0 z
07
0&
0g
#38
17
1&
1g
#39
1f
08
bz m
0;
1A
bx .
bx r
bx v
x-
05
0)
b100 i
b100 p
12
b100 y
bz000100 3
bz000100 k
bz000100 u
bz000100 {
bz000100 }
b0 /
b0 w
01
1>
1M
b10000000000000000000000000000000 #"
b0 s
b0 *
b0 t
b0 #
b0 :
b0 &"
b0 !"
b0 Q
b0 ""
07
0&
0g
#40
17
1&
1g
